jsontree/__init__.py
jsontree/jsontree.py
pyang_jsontree_plugin-0.1.dist-info/DESCRIPTION.rst
pyang_jsontree_plugin-0.1.dist-info/METADATA
pyang_jsontree_plugin-0.1.dist-info/RECORD
pyang_jsontree_plugin-0.1.dist-info/WHEEL
pyang_jsontree_plugin-0.1.dist-info/entry_points.txt
pyang_jsontree_plugin-0.1.dist-info/metadata.json
pyang_jsontree_plugin-0.1.dist-info/top_level.txt
