Metadata-Version: 2.0
Name: pyang-jsontree-plugin
Version: 0.1
Summary: A pyang plugin to produce a JSON representation of module trees for use in graph libraries
Home-page: https://github.com/cmoberg/pyang-jsontree-plugin
Author: Carl Moberg
Author-email: camoberg@cisco.com
License: New-style BSD
Keywords: yang,extraction,json
Platform: UNKNOWN
Requires-Dist: pyang
